[{"id":"pop-frag-0","name":"Sauvage","brand":"Dior","closestOurSite":"inspired-by-creed-aventus","aliases":[],"isDirectInspiration":false},{"id":"pop-frag-1","name":"Sauvage Elixir","brand":"Dior","closestOurSite":"inspired-by-creed-aventus","aliases":[],"isDirectInspiration":false},{"id":"pop-frag-2","name":"Sauvage Very Cool Spray","brand":"Dior","closestOurSite":"inspired-by-creed-aventus","aliases":[],"isDirectInspiration":false},{"id":"pop-frag-3","name":"Fahrenheit","brand":"Dior","closestOurSite":"inspired-by-creed-aventus","aliases":[],"isDirectInspiration":false},{"id":"pop-frag-4","name":"Dior Homme Original","brand":"Dior","closestOurSite":"inspired-by-jpg-le-male","aliases":[],"isDirectInspiration":false},{"id":"pop-frag-5","name":"Dior Homme Intense","brand":"Dior","closestOurSite":"inspired-by-jpg-le-male","aliases":[],"isDirectInspiration":false},{"id":"pop-frag-6","name":"Dior Homme Sport","brand":"Dior","closestOurSite":"inspired-by-creed-aventus","aliases":[],"isDirectInspiration":false},{"id":"pop-frag-7","name":"Dior Homme","brand":"Dior","closestOurSite":"inspired-by-creed-aventus","aliases":[],"isDirectInspiration":false},{"id":"pop-frag-8","name":"J'adore","brand":"Dior","closestOurSite":"inspired-by-jpg-le-male","aliases":[],"isDirectInspiration":false},{"id":"pop-frag-9","name":"J'adore L'Or","brand":"Dior","closestOurSite":"inspired-by-jpg-le-male","aliases":[],"isDirectInspiration":false},{"id":"pop-frag-10","name":"J'adore Infinissime","brand":"Dior","closestOurSite":"inspired-by-jpg-le-male","aliases":[],"isDirectInspiration":false},{"id":"pop-frag-11","name":"Miss Dior","brand":"Dior","closestOurSite":"inspired-by-jpg-le-male","aliases":[],"isDirectInspiration":false},{"id":"pop-frag-12","name":"Miss Dior Blooming Bouquet","brand":"Dior","closestOurSite":"inspired-by-jpg-le-male","aliases":[],"isDirectInspiration":false},{"id":"pop-frag-13","name":"Miss Dior Rose N'Roses","brand":"Dior","closestOurSite":"inspired-by-jpg-le-male","aliases":[],"isDirectInspiration":false},{"id":"pop-frag-14","name":"Hypnotic Poison","brand":"Dior","closestOurSite":"inspired-by-jpg-le-male","aliases":[],"isDirectInspiration":false},{"id":"pop-frag-15","name":"Pure Poison","brand":"Dior","closestOurSite":"inspired-by-jpg-le-male","aliases":[],"isDirectInspiration":false},{"id":"pop-frag-16","name":"Poison Girl","brand":"Dior","closestOurSite":"inspired-by-jpg-le-male","aliases":[],"isDirectInspiration":false},{"id":"pop-frag-17","name":"Dior Addict","brand":"Dior","closestOurSite":"inspired-by-jpg-le-male","aliases":[],"isDirectInspiration":false},{"id":"pop-frag-18","name":"Dune Pour Homme","brand":"Dior","closestOurSite":"inspired-by-creed-aventus","aliases":[],"isDirectInspiration":false},{"id":"pop-frag-19","name":"Dune Pour Femme","brand":"Dior","closestOurSite":"inspired-by-jpg-le-male","aliases":[],"isDirectInspiration":false},{"id":"pop-frag-20","name":"Bleu de Chanel","brand":"Chanel","closestOurSite":"inspired-by-creed-aventus","aliases":[],"isDirectInspiration":false},{"id":"pop-frag-21","name":"Allure Homme Sport","brand":"Chanel","closestOurSite":"inspired-by-creed-aventus","aliases":[],"isDirectInspiration":false},{"id":"pop-frag-22","name":"Allure Homme Sport Eau Extreme","brand":"Chanel","closestOurSite":"inspired-by-creed-aventus","aliases":[],"isDirectInspiration":false},{"id":"pop-frag-23","name":"Allure Homme Edition Blanche","brand":"Chanel","closestOurSite":"inspired-by-creed-aventus","aliases":[],"isDirectInspiration":false},{"id":"pop-frag-24","name":"Egoiste","brand":"Chanel","closestOurSite":"inspired-by-creed-aventus","aliases":[],"isDirectInspiration":false},{"id":"pop-frag-25","name":"Platinum Egoiste","brand":"Chanel","closestOurSite":"inspired-by-creed-aventus","aliases":[],"isDirectInspiration":false},{"id":"pop-frag-26","name":"Antaeus","brand":"Chanel","closestOurSite":"inspired-by-creed-aventus","aliases":[],"isDirectInspiration":false},{"id":"pop-frag-27","name":"Chanel No. 5","brand":"Chanel","closestOurSite":"inspired-by-jpg-le-male","aliases":[],"isDirectInspiration":false},{"id":"pop-frag-28","name":"Chanel No. 5 L'Eau","brand":"Chanel","closestOurSite":"inspired-by-jpg-le-male","aliases":[],"isDirectInspiration":false},{"id":"pop-frag-29","name":"Coco Mademoiselle","brand":"Chanel","closestOurSite":"inspired-by-jpg-le-male","aliases":[],"isDirectInspiration":false},{"id":"pop-frag-30","name":"Coco Mademoiselle Intense","brand":"Chanel","closestOurSite":"inspired-by-jpg-le-male","aliases":[],"isDirectInspiration":false},{"id":"pop-frag-31","name":"Chance Eau Tendre","brand":"Chanel","closestOurSite":"inspired-by-jpg-le-male","aliases":[],"isDirectInspiration":false},{"id":"pop-frag-32","name":"Chance Eau Fraiche","brand":"Chanel","closestOurSite":"inspired-by-jpg-le-male","aliases":[],"isDirectInspiration":false},{"id":"pop-frag-33","name":"Chance Eau Vive","brand":"Chanel","closestOurSite":"inspired-by-jpg-le-male","aliases":[],"isDirectInspiration":false},{"id":"pop-frag-34","name":"Coco Noir","brand":"Chanel","closestOurSite":"inspired-by-jpg-le-male","aliases":[],"isDirectInspiration":false},{"id":"pop-frag-35","name":"Gabrielle Chanel","brand":"Chanel","closestOurSite":"inspired-by-jpg-le-male","aliases":[],"isDirectInspiration":false},{"id":"pop-frag-36","name":"Cristalle","brand":"Chanel","closestOurSite":"inspired-by-jpg-le-male","aliases":[],"isDirectInspiration":false},{"id":"pop-frag-37","name":"Creed Aventus","brand":"Creed","closestOurSite":"inspired-by-creed-aventus","aliases":[],"isDirectInspiration":true},{"id":"pop-frag-38","name":"Aventus","brand":"Creed","closestOurSite":"inspired-by-creed-aventus","aliases":[],"isDirectInspiration":false},{"id":"pop-frag-39","name":"Aventus for Her","brand":"Creed","closestOurSite":"inspired-by-jpg-le-male","aliases":[],"isDirectInspiration":false},{"id":"pop-frag-40","name":"Green Irish Tweed","brand":"Creed","closestOurSite":"inspired-by-creed-aventus","aliases":[],"isDirectInspiration":false},{"id":"pop-frag-41","name":"Silver Mountain Water","brand":"Creed","closestOurSite":"inspired-by-creed-aventus","aliases":[],"isDirectInspiration":false},{"id":"pop-frag-42","name":"Millesime Imperial","brand":"Creed","closestOurSite":"inspired-by-creed-aventus","aliases":[],"isDirectInspiration":false},{"id":"pop-frag-43","name":"Royal Oud","brand":"Creed","closestOurSite":"inspired-by-creed-aventus","aliases":[],"isDirectInspiration":false},{"id":"pop-frag-44","name":"Viking","brand":"Creed","closestOurSite":"inspired-by-creed-aventus","aliases":[],"isDirectInspiration":false},{"id":"pop-frag-45","name":"Original Vetiver","brand":"Creed","closestOurSite":"inspired-by-creed-aventus","aliases":[],"isDirectInspiration":false},{"id":"pop-frag-46","name":"Original Santal","brand":"Creed","closestOurSite":"inspired-by-jpg-le-male","aliases":[],"isDirectInspiration":false},{"id":"pop-frag-47","name":"Virgin Island Water","brand":"Creed","closestOurSite":"inspired-by-creed-aventus","aliases":[],"isDirectInspiration":false},{"id":"pop-frag-48","name":"Love in White","brand":"Creed","closestOurSite":"inspired-by-jpg-le-male","aliases":[],"isDirectInspiration":false},{"id":"pop-frag-49","name":"Love in Black","brand":"Creed","closestOurSite":"inspired-by-jpg-le-male","aliases":[],"isDirectInspiration":false},{"id":"pop-frag-50","name":"Black Orchid","brand":"Tom Ford","closestOurSite":"inspired-by-jpg-le-male","aliases":[],"isDirectInspiration":false},{"id":"pop-frag-51","name":"Velvet Orchid","brand":"Tom Ford","closestOurSite":"inspired-by-jpg-le-male","aliases":[],"isDirectInspiration":false},{"id":"pop-frag-52","name":"Grey Vetiver","brand":"Tom Ford","closestOurSite":"inspired-by-creed-aventus","aliases":[],"isDirectInspiration":false},{"id":"pop-frag-53","name":"Noir Extreme","brand":"Tom Ford","closestOurSite":"inspired-by-jpg-le-male","aliases":[],"isDirectInspiration":false},{"id":"pop-frag-54","name":"Tobacco Vanille","brand":"Tom Ford","closestOurSite":"inspired-by-jpg-le-male","aliases":[],"isDirectInspiration":false},{"id":"pop-frag-55","name":"Oud Wood","brand":"Tom Ford","closestOurSite":"inspired-by-creed-aventus","aliases":[],"isDirectInspiration":false},{"id":"pop-frag-56","name":"Oud Wood Intense","brand":"Tom Ford","closestOurSite":"inspired-by-creed-aventus","aliases":[],"isDirectInspiration":false},{"id":"pop-frag-57","name":"Tuscan Leather","brand":"Tom Ford","closestOurSite":"inspired-by-creed-aventus","aliases":[],"isDirectInspiration":false},{"id":"pop-frag-58","name":"Tuscan Leather Intense","brand":"Tom Ford","closestOurSite":"inspired-by-creed-aventus","aliases":[],"isDirectInspiration":false},{"id":"pop-frag-59","name":"Lost Cherry","brand":"Tom Ford","closestOurSite":"inspired-by-jpg-le-male","aliases":[],"isDirectInspiration":false},{"id":"pop-frag-60","name":"Bitter Peach","brand":"Tom Ford","closestOurSite":"inspired-by-jpg-le-male","aliases":[],"isDirectInspiration":false},{"id":"pop-frag-61","name":"Electric Cherry","brand":"Tom Ford","closestOurSite":"inspired-by-jpg-le-male","aliases":[],"isDirectInspiration":false},{"id":"pop-frag-62","name":"Cherry Smoke","brand":"Tom Ford","closestOurSite":"inspired-by-jpg-le-male","aliases":[],"isDirectInspiration":false},{"id":"pop-frag-63","name":"Soleil Blanc","brand":"Tom Ford","closestOurSite":"inspired-by-jpg-le-male","aliases":[],"isDirectInspiration":false},{"id":"pop-frag-64","name":"Eau de Soleil Blanc","brand":"Tom Ford","closestOurSite":"inspired-by-creed-aventus","aliases":[],"isDirectInspiration":false},{"id":"pop-frag-65","name":"Neroli Portofino","brand":"Tom Ford","closestOurSite":"inspired-by-creed-aventus","aliases":[],"isDirectInspiration":false},{"id":"pop-frag-66","name":"Costa Azzurra","brand":"Tom Ford","closestOurSite":"inspired-by-creed-aventus","aliases":[],"isDirectInspiration":false},{"id":"pop-frag-67","name":"Mandarino di Amalfi","brand":"Tom Ford","closestOurSite":"inspired-by-creed-aventus","aliases":[],"isDirectInspiration":false},{"id":"pop-frag-68","name":"Beau de Jour","brand":"Tom Ford","closestOurSite":"inspired-by-creed-aventus","aliases":[],"isDirectInspiration":false},{"id":"pop-frag-69","name":"Fucking Fabulous","brand":"Tom Ford","closestOurSite":"inspired-by-jpg-le-male","aliases":[],"isDirectInspiration":false},{"id":"pop-frag-70","name":"Ombre Leather","brand":"Tom Ford","closestOurSite":"inspired-by-creed-aventus","aliases":[],"isDirectInspiration":false},{"id":"pop-frag-71","name":"Le Male","brand":"Jean Paul Gaultier","closestOurSite":"inspired-by-jpg-le-male","aliases":["jpg le male"],"isDirectInspiration":true},{"id":"pop-frag-72","name":"Le Male Le","brand":"Jean Paul Gaultier","closestOurSite":"inspired-by-jpg-le-male","aliases":["jpg le male le"],"isDirectInspiration":false},{"id":"pop-frag-73","name":"Ultra Male","brand":"Jean Paul Gaultier","closestOurSite":"inspired-by-jpg-le-male","aliases":["jpg ultra male"],"isDirectInspiration":false},{"id":"pop-frag-74","name":"Le Male Elixir","brand":"Jean Paul Gaultier","closestOurSite":"inspired-by-jpg-le-male","aliases":["jpg le male elixir"],"isDirectInspiration":false},{"id":"pop-frag-75","name":"Le Male Pride Edition","brand":"Jean Paul Gaultier","closestOurSite":"inspired-by-creed-aventus","aliases":["jpg le male pride edition"],"isDirectInspiration":false},{"id":"pop-frag-76","name":"Le Beau","brand":"Jean Paul Gaultier","closestOurSite":"inspired-by-creed-aventus","aliases":["jpg le beau"],"isDirectInspiration":false},{"id":"pop-frag-77","name":"Le Beau Le","brand":"Jean Paul Gaultier","closestOurSite":"inspired-by-jpg-le-male","aliases":["jpg le beau le"],"isDirectInspiration":false},{"id":"pop-frag-78","name":"Scandal Pour Homme","brand":"Jean Paul Gaultier","closestOurSite":"inspired-by-jpg-le-male","aliases":["jpg scandal pour homme"],"isDirectInspiration":false},{"id":"pop-frag-79","name":"Scandal Pour Homme Le","brand":"Jean Paul Gaultier","closestOurSite":"inspired-by-jpg-le-male","aliases":["jpg scandal pour homme le"],"isDirectInspiration":false},{"id":"pop-frag-80","name":"Classique","brand":"Jean Paul Gaultier","closestOurSite":"inspired-by-jpg-le-male","aliases":["jpg classique"],"isDirectInspiration":false},{"id":"pop-frag-81","name":"La Belle","brand":"Jean Paul Gaultier","closestOurSite":"inspired-by-jpg-le-male","aliases":["jpg la belle"],"isDirectInspiration":false},{"id":"pop-frag-82","name":"La Belle Le","brand":"Jean Paul Gaultier","closestOurSite":"inspired-by-jpg-le-male","aliases":["jpg la belle le"],"isDirectInspiration":false},{"id":"pop-frag-83","name":"Scandal","brand":"Jean Paul Gaultier","closestOurSite":"inspired-by-jpg-le-male","aliases":["jpg scandal"],"isDirectInspiration":false},{"id":"pop-frag-84","name":"Scandal Le","brand":"Jean Paul Gaultier","closestOurSite":"inspired-by-jpg-le-male","aliases":["jpg scandal le"],"isDirectInspiration":false},{"id":"pop-frag-85","name":"Y","brand":"Yves Saint Laurent","closestOurSite":"inspired-by-creed-aventus","aliases":["ysl y"],"isDirectInspiration":false},{"id":"pop-frag-86","name":"Y Le","brand":"Yves Saint Laurent","closestOurSite":"inspired-by-creed-aventus","aliases":["ysl y le"],"isDirectInspiration":false},{"id":"pop-frag-87","name":"Y Elixir","brand":"Yves Saint Laurent","closestOurSite":"inspired-by-creed-aventus","aliases":["ysl y elixir"],"isDirectInspiration":false},{"id":"pop-frag-88","name":"Y Live","brand":"Yves Saint Laurent","closestOurSite":"inspired-by-creed-aventus","aliases":["ysl y live"],"isDirectInspiration":false},{"id":"pop-frag-89","name":"La Nuit de L'Homme","brand":"Yves Saint Laurent","closestOurSite":"inspired-by-jpg-le-male","aliases":["ysl la nuit de l'homme"],"isDirectInspiration":false},{"id":"pop-frag-90","name":"La Nuit de L'Homme Bleu Electrique","brand":"Yves Saint Laurent","closestOurSite":"inspired-by-jpg-le-male","aliases":["ysl la nuit de l'homme bleu electrique"],"isDirectInspiration":false},{"id":"pop-frag-91","name":"La Nuit de L'Homme Le","brand":"Yves Saint Laurent","closestOurSite":"inspired-by-jpg-le-male","aliases":["ysl la nuit de l'homme le"],"isDirectInspiration":false},{"id":"pop-frag-92","name":"L'Homme","brand":"Yves Saint Laurent","closestOurSite":"inspired-by-creed-aventus","aliases":["ysl l'homme"],"isDirectInspiration":false},{"id":"pop-frag-93","name":"L'Homme Intense","brand":"Yves Saint Laurent","closestOurSite":"inspired-by-jpg-le-male","aliases":["ysl l'homme intense"],"isDirectInspiration":false},{"id":"pop-frag-94","name":"Kouros","brand":"Yves Saint Laurent","closestOurSite":"inspired-by-creed-aventus","aliases":["ysl kouros"],"isDirectInspiration":false},{"id":"pop-frag-95","name":"Body Kouros","brand":"Yves Saint Laurent","closestOurSite":"inspired-by-jpg-le-male","aliases":["ysl body kouros"],"isDirectInspiration":false},{"id":"pop-frag-96","name":"Black Opium","brand":"Yves Saint Laurent","closestOurSite":"inspired-by-jpg-le-male","aliases":["ysl black opium"],"isDirectInspiration":false},{"id":"pop-frag-97","name":"Black Opium Extreme","brand":"Yves Saint Laurent","closestOurSite":"inspired-by-jpg-le-male","aliases":["ysl black opium extreme"],"isDirectInspiration":false},{"id":"pop-frag-98","name":"Black Opium Neon","brand":"Yves Saint Laurent","closestOurSite":"inspired-by-jpg-le-male","aliases":["ysl black opium neon"],"isDirectInspiration":false},{"id":"pop-frag-99","name":"Black Opium Illicit Green","brand":"Yves Saint Laurent","closestOurSite":"inspired-by-jpg-le-male","aliases":["ysl black opium illicit green"],"isDirectInspiration":false},{"id":"pop-frag-100","name":"Black Opium Over Red","brand":"Yves Saint Laurent","closestOurSite":"inspired-by-jpg-le-male","aliases":["ysl black opium over red"],"isDirectInspiration":false},{"id":"pop-frag-101","name":"Libre","brand":"Yves Saint Laurent","closestOurSite":"inspired-by-jpg-le-male","aliases":["ysl libre"],"isDirectInspiration":false},{"id":"pop-frag-102","name":"Libre Intense","brand":"Yves Saint Laurent","closestOurSite":"inspired-by-jpg-le-male","aliases":["ysl libre intense"],"isDirectInspiration":false},{"id":"pop-frag-103","name":"Libre Le","brand":"Yves Saint Laurent","closestOurSite":"inspired-by-jpg-le-male","aliases":["ysl libre le"],"isDirectInspiration":false},{"id":"pop-frag-104","name":"Mon Paris","brand":"Yves Saint Laurent","closestOurSite":"inspired-by-jpg-le-male","aliases":["ysl mon paris"],"isDirectInspiration":false},{"id":"pop-frag-105","name":"Opium","brand":"Yves Saint Laurent","closestOurSite":"inspired-by-jpg-le-male","aliases":["ysl opium"],"isDirectInspiration":false},{"id":"pop-frag-106","name":"Rive Gauche","brand":"Yves Saint Laurent","closestOurSite":"inspired-by-jpg-le-male","aliases":["ysl rive gauche"],"isDirectInspiration":false},{"id":"pop-frag-107","name":"Eros","brand":"Versace","closestOurSite":"inspired-by-jpg-le-male","aliases":[],"isDirectInspiration":false},{"id":"pop-frag-108","name":"Eros Flame","brand":"Versace","closestOurSite":"inspired-by-jpg-le-male","aliases":[],"isDirectInspiration":false},{"id":"pop-frag-109","name":"Eros Energy","brand":"Versace","closestOurSite":"inspired-by-creed-aventus","aliases":[],"isDirectInspiration":false},{"id":"pop-frag-110","name":"Dylan Blue Pour Homme","brand":"Versace","closestOurSite":"inspired-by-creed-aventus","aliases":[],"isDirectInspiration":false},{"id":"pop-frag-111","name":"Dylan Blue Pour Femme","brand":"Versace","closestOurSite":"inspired-by-jpg-le-male","aliases":[],"isDirectInspiration":false},{"id":"pop-frag-112","name":"Versace Pour Homme","brand":"Versace","closestOurSite":"inspired-by-creed-aventus","aliases":[],"isDirectInspiration":false},{"id":"pop-frag-113","name":"Versace Man Eau Fraiche","brand":"Versace","closestOurSite":"inspired-by-creed-aventus","aliases":[],"isDirectInspiration":false},{"id":"pop-frag-114","name":"The Dreamer","brand":"Versace","closestOurSite":"inspired-by-jpg-le-male","aliases":[],"isDirectInspiration":false},{"id":"pop-frag-115","name":"Bright Crystal","brand":"Versace","closestOurSite":"inspired-by-jpg-le-male","aliases":[],"isDirectInspiration":false},{"id":"pop-frag-116","name":"Bright Crystal Absolu","brand":"Versace","closestOurSite":"inspired-by-jpg-le-male","aliases":[],"isDirectInspiration":false},{"id":"pop-frag-117","name":"Crystal Noir","brand":"Versace","closestOurSite":"inspired-by-jpg-le-male","aliases":[],"isDirectInspiration":false},{"id":"pop-frag-118","name":"Yellow Diamond","brand":"Versace","closestOurSite":"inspired-by-jpg-le-male","aliases":[],"isDirectInspiration":false},{"id":"pop-frag-119","name":"Acqua di Gio","brand":"Giorgio Armani","closestOurSite":"inspired-by-creed-aventus","aliases":[],"isDirectInspiration":false},{"id":"pop-frag-120","name":"Acqua di Gio Profumo","brand":"Giorgio Armani","closestOurSite":"inspired-by-creed-aventus","aliases":[],"isDirectInspiration":false},{"id":"pop-frag-121","name":"Acqua di Gio Profondo","brand":"Giorgio Armani","closestOurSite":"inspired-by-creed-aventus","aliases":[],"isDirectInspiration":false},{"id":"pop-frag-122","name":"Armani Code","brand":"Giorgio Armani","closestOurSite":"inspired-by-jpg-le-male","aliases":[],"isDirectInspiration":false},{"id":"pop-frag-123","name":"Armani Code Absolu","brand":"Giorgio Armani","closestOurSite":"inspired-by-jpg-le-male","aliases":[],"isDirectInspiration":false},{"id":"pop-frag-124","name":"Stronger With You","brand":"Giorgio Armani","closestOurSite":"inspired-by-jpg-le-male","aliases":[],"isDirectInspiration":false},{"id":"pop-frag-125","name":"Stronger With You Intensely","brand":"Giorgio Armani","closestOurSite":"inspired-by-jpg-le-male","aliases":[],"isDirectInspiration":false},{"id":"pop-frag-126","name":"Stronger With You Absolutely","brand":"Giorgio Armani","closestOurSite":"inspired-by-jpg-le-male","aliases":[],"isDirectInspiration":false},{"id":"pop-frag-127","name":"Stronger With You Only","brand":"Giorgio Armani","closestOurSite":"inspired-by-jpg-le-male","aliases":[],"isDirectInspiration":false},{"id":"pop-frag-128","name":"Stronger With You Leather","brand":"Giorgio Armani","closestOurSite":"inspired-by-jpg-le-male","aliases":[],"isDirectInspiration":false},{"id":"pop-frag-129","name":"Stronger With You Amber","brand":"Giorgio Armani","closestOurSite":"inspired-by-jpg-le-male","aliases":[],"isDirectInspiration":false},{"id":"pop-frag-130","name":"Si","brand":"Giorgio Armani","closestOurSite":"inspired-by-jpg-le-male","aliases":[],"isDirectInspiration":false},{"id":"pop-frag-131","name":"Si Intense","brand":"Giorgio Armani","closestOurSite":"inspired-by-jpg-le-male","aliases":[],"isDirectInspiration":false},{"id":"pop-frag-132","name":"Si Passione","brand":"Giorgio Armani","closestOurSite":"inspired-by-jpg-le-male","aliases":[],"isDirectInspiration":false},{"id":"pop-frag-133","name":"My Way","brand":"Giorgio Armani","closestOurSite":"inspired-by-jpg-le-male","aliases":[],"isDirectInspiration":false},{"id":"pop-frag-134","name":"My Way Intense","brand":"Giorgio Armani","closestOurSite":"inspired-by-jpg-le-male","aliases":[],"isDirectInspiration":false},{"id":"pop-frag-135","name":"Armani Mania Pour Homme","brand":"Giorgio Armani","closestOurSite":"inspired-by-creed-aventus","aliases":[],"isDirectInspiration":false},{"id":"pop-frag-136","name":"1 Million","brand":"Paco Rabanne","closestOurSite":"inspired-by-jpg-le-male","aliases":[],"isDirectInspiration":false},{"id":"pop-frag-137","name":"1 Million Lucky","brand":"Paco Rabanne","closestOurSite":"inspired-by-jpg-le-male","aliases":[],"isDirectInspiration":false},{"id":"pop-frag-138","name":"1 Million Privé","brand":"Paco Rabanne","closestOurSite":"inspired-by-jpg-le-male","aliases":[],"isDirectInspiration":false},{"id":"pop-frag-139","name":"1 Million Elixir","brand":"Paco Rabanne","closestOurSite":"inspired-by-jpg-le-male","aliases":[],"isDirectInspiration":false},{"id":"pop-frag-140","name":"1 Million Royal","brand":"Paco Rabanne","closestOurSite":"inspired-by-jpg-le-male","aliases":[],"isDirectInspiration":false},{"id":"pop-frag-141","name":"Invictus","brand":"Paco Rabanne","closestOurSite":"inspired-by-creed-aventus","aliases":[],"isDirectInspiration":false},{"id":"pop-frag-142","name":"Invictus Legend","brand":"Paco Rabanne","closestOurSite":"inspired-by-creed-aventus","aliases":[],"isDirectInspiration":false},{"id":"pop-frag-143","name":"Invictus Victory","brand":"Paco Rabanne","closestOurSite":"inspired-by-jpg-le-male","aliases":[],"isDirectInspiration":false},{"id":"pop-frag-144","name":"Invictus Victory Elixir","brand":"Paco Rabanne","closestOurSite":"inspired-by-jpg-le-male","aliases":[],"isDirectInspiration":false},{"id":"pop-frag-145","name":"Phantom","brand":"Paco Rabanne","closestOurSite":"inspired-by-jpg-le-male","aliases":[],"isDirectInspiration":false},{"id":"pop-frag-146","name":"Phantom Intense","brand":"Paco Rabanne","closestOurSite":"inspired-by-jpg-le-male","aliases":[],"isDirectInspiration":false},{"id":"pop-frag-147","name":"Black XS Pour Homme","brand":"Paco Rabanne","closestOurSite":"inspired-by-jpg-le-male","aliases":[],"isDirectInspiration":false},{"id":"pop-frag-148","name":"Black XS Pour Femme","brand":"Paco Rabanne","closestOurSite":"inspired-by-jpg-le-male","aliases":[],"isDirectInspiration":false},{"id":"pop-frag-149","name":"Olympea","brand":"Paco Rabanne","closestOurSite":"inspired-by-jpg-le-male","aliases":[],"isDirectInspiration":false},{"id":"pop-frag-150","name":"Olympea Intense","brand":"Paco Rabanne","closestOurSite":"inspired-by-jpg-le-male","aliases":[],"isDirectInspiration":false},{"id":"pop-frag-151","name":"Olympea Legend","brand":"Paco Rabanne","closestOurSite":"inspired-by-jpg-le-male","aliases":[],"isDirectInspiration":false},{"id":"pop-frag-152","name":"Lady Million","brand":"Paco Rabanne","closestOurSite":"inspired-by-jpg-le-male","aliases":[],"isDirectInspiration":false},{"id":"pop-frag-153","name":"Lady Million Lucky","brand":"Paco Rabanne","closestOurSite":"inspired-by-jpg-le-male","aliases":[],"isDirectInspiration":false},{"id":"pop-frag-154","name":"Lady Million Empire","brand":"Paco Rabanne","closestOurSite":"inspired-by-jpg-le-male","aliases":[],"isDirectInspiration":false},{"id":"pop-frag-155","name":"Lady Million Royal","brand":"Paco Rabanne","closestOurSite":"inspired-by-jpg-le-male","aliases":[],"isDirectInspiration":false},{"id":"pop-frag-156","name":"Fame","brand":"Paco Rabanne","closestOurSite":"inspired-by-jpg-le-male","aliases":[],"isDirectInspiration":false},{"id":"pop-frag-157","name":"L'Homme Prada","brand":"Prada","closestOurSite":"inspired-by-creed-aventus","aliases":[],"isDirectInspiration":false},{"id":"pop-frag-158","name":"L'Homme Prada L'Eau","brand":"Prada","closestOurSite":"inspired-by-creed-aventus","aliases":[],"isDirectInspiration":false},{"id":"pop-frag-159","name":"L'Homme Prada Intense","brand":"Prada","closestOurSite":"inspired-by-jpg-le-male","aliases":[],"isDirectInspiration":false},{"id":"pop-frag-160","name":"Luna Rossa","brand":"Prada","closestOurSite":"inspired-by-creed-aventus","aliases":[],"isDirectInspiration":false},{"id":"pop-frag-161","name":"Luna Rossa Sport","brand":"Prada","closestOurSite":"inspired-by-jpg-le-male","aliases":[],"isDirectInspiration":false},{"id":"pop-frag-162","name":"Luna Rossa Carbon","brand":"Prada","closestOurSite":"inspired-by-creed-aventus","aliases":[],"isDirectInspiration":false},{"id":"pop-frag-163","name":"Luna Rossa Black","brand":"Prada","closestOurSite":"inspired-by-jpg-le-male","aliases":[],"isDirectInspiration":false},{"id":"pop-frag-164","name":"Luna Rossa Ocean","brand":"Prada","closestOurSite":"inspired-by-creed-aventus","aliases":[],"isDirectInspiration":false},{"id":"pop-frag-165","name":"Prada Candy","brand":"Prada","closestOurSite":"inspired-by-jpg-le-male","aliases":[],"isDirectInspiration":false},{"id":"pop-frag-166","name":"Prada Paradoxe","brand":"Prada","closestOurSite":"inspired-by-jpg-le-male","aliases":[],"isDirectInspiration":false},{"id":"pop-frag-167","name":"Prada Paradoxe Intense","brand":"Prada","closestOurSite":"inspired-by-jpg-le-male","aliases":[],"isDirectInspiration":false},{"id":"pop-frag-168","name":"Amber Pour Homme","brand":"Prada","closestOurSite":"inspired-by-creed-aventus","aliases":[],"isDirectInspiration":false},{"id":"pop-frag-169","name":"Baccarat Rouge 540","brand":"Maison Francis Kurkdjian","closestOurSite":"inspired-by-jpg-le-male","aliases":["mfk baccarat rouge 540"],"isDirectInspiration":false},{"id":"pop-frag-170","name":"Baccarat Rouge 540 Extrait","brand":"Maison Francis Kurkdjian","closestOurSite":"inspired-by-jpg-le-male","aliases":["mfk baccarat rouge 540 extrait"],"isDirectInspiration":false},{"id":"pop-frag-171","name":"Grand Soir","brand":"Maison Francis Kurkdjian","closestOurSite":"inspired-by-jpg-le-male","aliases":["mfk grand soir"],"isDirectInspiration":false},{"id":"pop-frag-172","name":"Gentle Fluidity Gold","brand":"Maison Francis Kurkdjian","closestOurSite":"inspired-by-jpg-le-male","aliases":["mfk gentle fluidity gold"],"isDirectInspiration":false},{"id":"pop-frag-173","name":"Gentle Fluidity Silver","brand":"Maison Francis Kurkdjian","closestOurSite":"inspired-by-creed-aventus","aliases":["mfk gentle fluidity silver"],"isDirectInspiration":false},{"id":"pop-frag-174","name":"Amyris Homme","brand":"Maison Francis Kurkdjian","closestOurSite":"inspired-by-creed-aventus","aliases":["mfk amyris homme"],"isDirectInspiration":false},{"id":"pop-frag-175","name":"Oud Satin Mood","brand":"Maison Francis Kurkdjian","closestOurSite":"inspired-by-jpg-le-male","aliases":["mfk oud satin mood"],"isDirectInspiration":false},{"id":"pop-frag-176","name":"Terre d'Hermès","brand":"Hermès","closestOurSite":"inspired-by-creed-aventus","aliases":[],"isDirectInspiration":false},{"id":"pop-frag-177","name":"Terre d'Hermès Eau Givrée","brand":"Hermès","closestOurSite":"inspired-by-creed-aventus","aliases":[],"isDirectInspiration":false},{"id":"pop-frag-178","name":"Terre d'Hermès Eau Intense Vetiver","brand":"Hermès","closestOurSite":"inspired-by-creed-aventus","aliases":[],"isDirectInspiration":false},{"id":"pop-frag-179","name":"H24","brand":"Hermès","closestOurSite":"inspired-by-creed-aventus","aliases":[],"isDirectInspiration":false},{"id":"pop-frag-180","name":"Voyage d'Hermès","brand":"Hermès","closestOurSite":"inspired-by-creed-aventus","aliases":[],"isDirectInspiration":false},{"id":"pop-frag-181","name":"Twilly d'Hermès","brand":"Hermès","closestOurSite":"inspired-by-jpg-le-male","aliases":[],"isDirectInspiration":false},{"id":"pop-frag-182","name":"Eau des Merveilles","brand":"Hermès","closestOurSite":"inspired-by-jpg-le-male","aliases":[],"isDirectInspiration":false},{"id":"pop-frag-183","name":"Kelly Calèche","brand":"Hermès","closestOurSite":"inspired-by-jpg-le-male","aliases":[],"isDirectInspiration":false},{"id":"pop-frag-184","name":"Spicebomb","brand":"Viktor & Rolf","closestOurSite":"inspired-by-creed-aventus","aliases":[],"isDirectInspiration":false},{"id":"pop-frag-185","name":"Spicebomb Extreme","brand":"Viktor & Rolf","closestOurSite":"inspired-by-jpg-le-male","aliases":[],"isDirectInspiration":false},{"id":"pop-frag-186","name":"Spicebomb Infrared","brand":"Viktor & Rolf","closestOurSite":"inspired-by-creed-aventus","aliases":[],"isDirectInspiration":false},{"id":"pop-frag-187","name":"Spicebomb Night Vision","brand":"Viktor & Rolf","closestOurSite":"inspired-by-creed-aventus","aliases":[],"isDirectInspiration":false},{"id":"pop-frag-188","name":"Flowerbomb","brand":"Viktor & Rolf","closestOurSite":"inspired-by-jpg-le-male","aliases":[],"isDirectInspiration":false},{"id":"pop-frag-189","name":"Flowerbomb Nectar","brand":"Viktor & Rolf","closestOurSite":"inspired-by-jpg-le-male","aliases":[],"isDirectInspiration":false},{"id":"pop-frag-190","name":"Flowerbomb Ruby Orchid","brand":"Viktor & Rolf","closestOurSite":"inspired-by-jpg-le-male","aliases":[],"isDirectInspiration":false},{"id":"pop-frag-191","name":"Bonbon","brand":"Viktor & Rolf","closestOurSite":"inspired-by-jpg-le-male","aliases":[],"isDirectInspiration":false},{"id":"pop-frag-192","name":"A*Men","brand":"Mugler","closestOurSite":"inspired-by-jpg-le-male","aliases":[],"isDirectInspiration":false},{"id":"pop-frag-193","name":"A*Men Pure Malt","brand":"Mugler","closestOurSite":"inspired-by-jpg-le-male","aliases":[],"isDirectInspiration":false},{"id":"pop-frag-194","name":"A*Men Pure Havane","brand":"Mugler","closestOurSite":"inspired-by-jpg-le-male","aliases":[],"isDirectInspiration":false},{"id":"pop-frag-195","name":"Alien","brand":"Mugler","closestOurSite":"inspired-by-jpg-le-male","aliases":[],"isDirectInspiration":false},{"id":"pop-frag-196","name":"Alien Goddess","brand":"Mugler","closestOurSite":"inspired-by-jpg-le-male","aliases":[],"isDirectInspiration":false},{"id":"pop-frag-197","name":"Angel","brand":"Mugler","closestOurSite":"inspired-by-jpg-le-male","aliases":[],"isDirectInspiration":false},{"id":"pop-frag-198","name":"Angel Nova","brand":"Mugler","closestOurSite":"inspired-by-jpg-le-male","aliases":[],"isDirectInspiration":false},{"id":"pop-frag-199","name":"Gentleman","brand":"Givenchy","closestOurSite":"inspired-by-creed-aventus","aliases":[],"isDirectInspiration":false},{"id":"pop-frag-200","name":"Gentleman Reserve Privee","brand":"Givenchy","closestOurSite":"inspired-by-jpg-le-male","aliases":[],"isDirectInspiration":false},{"id":"pop-frag-201","name":"Gentleman Boisee","brand":"Givenchy","closestOurSite":"inspired-by-creed-aventus","aliases":[],"isDirectInspiration":false},{"id":"pop-frag-202","name":"Gentleman Society","brand":"Givenchy","closestOurSite":"inspired-by-creed-aventus","aliases":[],"isDirectInspiration":false},{"id":"pop-frag-203","name":"Givenchy Pi","brand":"Givenchy","closestOurSite":"inspired-by-jpg-le-male","aliases":[],"isDirectInspiration":false},{"id":"pop-frag-204","name":"Amarige","brand":"Givenchy","closestOurSite":"inspired-by-jpg-le-male","aliases":[],"isDirectInspiration":false},{"id":"pop-frag-205","name":"Organza","brand":"Givenchy","closestOurSite":"inspired-by-jpg-le-male","aliases":[],"isDirectInspiration":false},{"id":"pop-frag-206","name":"L'Interdit","brand":"Givenchy","closestOurSite":"inspired-by-jpg-le-male","aliases":[],"isDirectInspiration":false},{"id":"pop-frag-207","name":"L'Interdit Intense","brand":"Givenchy","closestOurSite":"inspired-by-jpg-le-male","aliases":[],"isDirectInspiration":false},{"id":"pop-frag-208","name":"Guilty Pour Homme","brand":"Gucci","closestOurSite":"inspired-by-creed-aventus","aliases":[],"isDirectInspiration":false},{"id":"pop-frag-209","name":"Guilty Pour Homme Elixir","brand":"Gucci","closestOurSite":"inspired-by-creed-aventus","aliases":[],"isDirectInspiration":false},{"id":"pop-frag-210","name":"Guilty Pour Femme","brand":"Gucci","closestOurSite":"inspired-by-jpg-le-male","aliases":[],"isDirectInspiration":false},{"id":"pop-frag-211","name":"Guilty Pour Femme Intense","brand":"Gucci","closestOurSite":"inspired-by-jpg-le-male","aliases":[],"isDirectInspiration":false},{"id":"pop-frag-212","name":"Gucci Bloom","brand":"Gucci","closestOurSite":"inspired-by-jpg-le-male","aliases":[],"isDirectInspiration":false},{"id":"pop-frag-213","name":"Gucci Flora Gorgeous Gardenia","brand":"Gucci","closestOurSite":"inspired-by-jpg-le-male","aliases":[],"isDirectInspiration":false},{"id":"pop-frag-214","name":"Gucci Flora Gorgeous Jasmine","brand":"Gucci","closestOurSite":"inspired-by-jpg-le-male","aliases":[],"isDirectInspiration":false},{"id":"pop-frag-215","name":"Gucci Flora Gorgeous Magnolia","brand":"Gucci","closestOurSite":"inspired-by-jpg-le-male","aliases":[],"isDirectInspiration":false},{"id":"pop-frag-216","name":"Gucci Rush","brand":"Gucci","closestOurSite":"inspired-by-jpg-le-male","aliases":[],"isDirectInspiration":false},{"id":"pop-frag-217","name":"Light Blue Pour Homme","brand":"Dolce & Gabbana","closestOurSite":"inspired-by-creed-aventus","aliases":["dg light blue pour homme","d&g light blue pour homme"],"isDirectInspiration":false},{"id":"pop-frag-218","name":"Light Blue Pour Homme Intense","brand":"Dolce & Gabbana","closestOurSite":"inspired-by-creed-aventus","aliases":["dg light blue pour homme intense","d&g light blue pour homme intense"],"isDirectInspiration":false},{"id":"pop-frag-219","name":"Light Blue Pour Femme","brand":"Dolce & Gabbana","closestOurSite":"inspired-by-jpg-le-male","aliases":["dg light blue pour femme","d&g light blue pour femme"],"isDirectInspiration":false},{"id":"pop-frag-220","name":"Light Blue Pour Femme Intense","brand":"Dolce & Gabbana","closestOurSite":"inspired-by-jpg-le-male","aliases":["dg light blue pour femme intense","d&g light blue pour femme intense"],"isDirectInspiration":false},{"id":"pop-frag-221","name":"The One Pour Homme","brand":"Dolce & Gabbana","closestOurSite":"inspired-by-jpg-le-male","aliases":["dg the one pour homme","d&g the one pour homme"],"isDirectInspiration":false},{"id":"pop-frag-222","name":"The One Pour Homme Royal Night","brand":"Dolce & Gabbana","closestOurSite":"inspired-by-jpg-le-male","aliases":["dg the one pour homme royal night","d&g the one pour homme royal night"],"isDirectInspiration":false},{"id":"pop-frag-223","name":"The One Pour Homme Luminous Night","brand":"Dolce & Gabbana","closestOurSite":"inspired-by-jpg-le-male","aliases":["dg the one pour homme luminous night","d&g the one pour homme luminous night"],"isDirectInspiration":false},{"id":"pop-frag-224","name":"The One Pour Femme","brand":"Dolce & Gabbana","closestOurSite":"inspired-by-jpg-le-male","aliases":["dg the one pour femme","d&g the one pour femme"],"isDirectInspiration":false},{"id":"pop-frag-225","name":"K by Dolce & Gabbana","brand":"Dolce & Gabbana","closestOurSite":"inspired-by-creed-aventus","aliases":["dg k by dolce & gabbana","d&g k by dolce & gabbana"],"isDirectInspiration":false},{"id":"pop-frag-226","name":"Devotion","brand":"Dolce & Gabbana","closestOurSite":"inspired-by-jpg-le-male","aliases":["dg devotion","d&g devotion"],"isDirectInspiration":false},{"id":"pop-frag-227","name":"Elysium","brand":"Roja Parfums","closestOurSite":"inspired-by-creed-aventus","aliases":[],"isDirectInspiration":false},{"id":"pop-frag-228","name":"Elysium Intense","brand":"Roja Parfums","closestOurSite":"inspired-by-creed-aventus","aliases":[],"isDirectInspiration":false},{"id":"pop-frag-229","name":"Enigma Pour Homme","brand":"Roja Parfums","closestOurSite":"inspired-by-jpg-le-male","aliases":[],"isDirectInspiration":false},{"id":"pop-frag-230","name":"Apex Pour Homme","brand":"Roja Parfums","closestOurSite":"inspired-by-creed-aventus","aliases":[],"isDirectInspiration":false},{"id":"pop-frag-231","name":"Reflection Man","brand":"Amouage","closestOurSite":"inspired-by-creed-aventus","aliases":[],"isDirectInspiration":false},{"id":"pop-frag-232","name":"Interlude Man","brand":"Amouage","closestOurSite":"inspired-by-creed-aventus","aliases":[],"isDirectInspiration":false},{"id":"pop-frag-233","name":"Interlude Man 53","brand":"Amouage","closestOurSite":"inspired-by-creed-aventus","aliases":[],"isDirectInspiration":false},{"id":"pop-frag-234","name":"Jubilation XXV Man","brand":"Amouage","closestOurSite":"inspired-by-jpg-le-male","aliases":[],"isDirectInspiration":false},{"id":"pop-frag-235","name":"Lyric Man","brand":"Amouage","closestOurSite":"inspired-by-jpg-le-male","aliases":[],"isDirectInspiration":false},{"id":"pop-frag-236","name":"Beach Hut Man","brand":"Amouage","closestOurSite":"inspired-by-creed-aventus","aliases":[],"isDirectInspiration":false},{"id":"pop-frag-237","name":"Layton","brand":"Parfums de Marly","closestOurSite":"inspired-by-jpg-le-male","aliases":["pdm layton"],"isDirectInspiration":false},{"id":"pop-frag-238","name":"Layton Exclusif","brand":"Parfums de Marly","closestOurSite":"inspired-by-jpg-le-male","aliases":["pdm layton exclusif"],"isDirectInspiration":false},{"id":"pop-frag-239","name":"Herod","brand":"Parfums de Marly","closestOurSite":"inspired-by-jpg-le-male","aliases":["pdm herod"],"isDirectInspiration":false},{"id":"pop-frag-240","name":"Pegasus","brand":"Parfums de Marly","closestOurSite":"inspired-by-jpg-le-male","aliases":["pdm pegasus"],"isDirectInspiration":false},{"id":"pop-frag-241","name":"Pegasus Exclusif","brand":"Parfums de Marly","closestOurSite":"inspired-by-jpg-le-male","aliases":["pdm pegasus exclusif"],"isDirectInspiration":false},{"id":"pop-frag-242","name":"Percival","brand":"Parfums de Marly","closestOurSite":"inspired-by-creed-aventus","aliases":["pdm percival"],"isDirectInspiration":false},{"id":"pop-frag-243","name":"Carlisle","brand":"Parfums de Marly","closestOurSite":"inspired-by-jpg-le-male","aliases":["pdm carlisle"],"isDirectInspiration":false},{"id":"pop-frag-244","name":"Greenley","brand":"Parfums de Marly","closestOurSite":"inspired-by-creed-aventus","aliases":["pdm greenley"],"isDirectInspiration":false},{"id":"pop-frag-245","name":"Sedley","brand":"Parfums de Marly","closestOurSite":"inspired-by-creed-aventus","aliases":["pdm sedley"],"isDirectInspiration":false},{"id":"pop-frag-246","name":"Haltane","brand":"Parfums de Marly","closestOurSite":"inspired-by-creed-aventus","aliases":["pdm haltane"],"isDirectInspiration":false},{"id":"pop-frag-247","name":"Delina","brand":"Parfums de Marly","closestOurSite":"inspired-by-jpg-le-male","aliases":["pdm delina"],"isDirectInspiration":false},{"id":"pop-frag-248","name":"Delina Exclusif","brand":"Parfums de Marly","closestOurSite":"inspired-by-jpg-le-male","aliases":["pdm delina exclusif"],"isDirectInspiration":false},{"id":"pop-frag-249","name":"Valaya","brand":"Parfums de Marly","closestOurSite":"inspired-by-jpg-le-male","aliases":["pdm valaya"],"isDirectInspiration":false},{"id":"pop-frag-250","name":"Oajan","brand":"Parfums de Marly","closestOurSite":"inspired-by-jpg-le-male","aliases":["pdm oajan"],"isDirectInspiration":false},{"id":"pop-frag-251","name":"Althair","brand":"Parfums de Marly","closestOurSite":"inspired-by-jpg-le-male","aliases":["pdm althair"],"isDirectInspiration":false},{"id":"pop-frag-252","name":"Love Don't Be Shy","brand":"Kilian","closestOurSite":"inspired-by-jpg-le-male","aliases":[],"isDirectInspiration":false},{"id":"pop-frag-253","name":"Black Phantom","brand":"Kilian","closestOurSite":"inspired-by-jpg-le-male","aliases":[],"isDirectInspiration":false},{"id":"pop-frag-254","name":"Angels' Share","brand":"Kilian","closestOurSite":"inspired-by-jpg-le-male","aliases":[],"isDirectInspiration":false},{"id":"pop-frag-255","name":"Apple Brandy","brand":"Kilian","closestOurSite":"inspired-by-jpg-le-male","aliases":[],"isDirectInspiration":false},{"id":"pop-frag-256","name":"Sacred Wood","brand":"Kilian","closestOurSite":"inspired-by-creed-aventus","aliases":[],"isDirectInspiration":false},{"id":"pop-frag-257","name":"Straight to Heaven","brand":"Kilian","closestOurSite":"inspired-by-creed-aventus","aliases":[],"isDirectInspiration":false},{"id":"pop-frag-258","name":"Gypsy Water","brand":"Byredo","closestOurSite":"inspired-by-creed-aventus","aliases":[],"isDirectInspiration":false},{"id":"pop-frag-259","name":"Bal d'Afrique","brand":"Byredo","closestOurSite":"inspired-by-creed-aventus","aliases":[],"isDirectInspiration":false},{"id":"pop-frag-260","name":"Mojave Ghost","brand":"Byredo","closestOurSite":"inspired-by-jpg-le-male","aliases":[],"isDirectInspiration":false},{"id":"pop-frag-261","name":"Bibliothèque","brand":"Byredo","closestOurSite":"inspired-by-jpg-le-male","aliases":[],"isDirectInspiration":false},{"id":"pop-frag-262","name":"Rose of No Man's Land","brand":"Byredo","closestOurSite":"inspired-by-jpg-le-male","aliases":[],"isDirectInspiration":false},{"id":"pop-frag-263","name":"Wood Sage & Sea Salt","brand":"Jo Malone","closestOurSite":"inspired-by-creed-aventus","aliases":[],"isDirectInspiration":false},{"id":"pop-frag-264","name":"English Pear & Freesia","brand":"Jo Malone","closestOurSite":"inspired-by-jpg-le-male","aliases":[],"isDirectInspiration":false},{"id":"pop-frag-265","name":"Pomegranate Noir","brand":"Jo Malone","closestOurSite":"inspired-by-jpg-le-male","aliases":[],"isDirectInspiration":false},{"id":"pop-frag-266","name":"Blackberry & Bay","brand":"Jo Malone","closestOurSite":"inspired-by-creed-aventus","aliases":[],"isDirectInspiration":false},{"id":"pop-frag-267","name":"Good Girl","brand":"Carolina Herrera","closestOurSite":"inspired-by-jpg-le-male","aliases":[],"isDirectInspiration":false},{"id":"pop-frag-268","name":"Good Girl Supreme","brand":"Carolina Herrera","closestOurSite":"inspired-by-jpg-le-male","aliases":[],"isDirectInspiration":false},{"id":"pop-frag-269","name":"Good Girl Blush","brand":"Carolina Herrera","closestOurSite":"inspired-by-jpg-le-male","aliases":[],"isDirectInspiration":false},{"id":"pop-frag-270","name":"Very Good Girl","brand":"Carolina Herrera","closestOurSite":"inspired-by-jpg-le-male","aliases":[],"isDirectInspiration":false},{"id":"pop-frag-271","name":"Bad Boy","brand":"Carolina Herrera","closestOurSite":"inspired-by-jpg-le-male","aliases":[],"isDirectInspiration":false},{"id":"pop-frag-272","name":"Bad Boy Cobalt","brand":"Carolina Herrera","closestOurSite":"inspired-by-creed-aventus","aliases":[],"isDirectInspiration":false},{"id":"pop-frag-273","name":"Bad Boy Le","brand":"Carolina Herrera","closestOurSite":"inspired-by-jpg-le-male","aliases":[],"isDirectInspiration":false},{"id":"pop-frag-274","name":"Bad Boy Extreme","brand":"Carolina Herrera","closestOurSite":"inspired-by-jpg-le-male","aliases":[],"isDirectInspiration":false},{"id":"pop-frag-275","name":"212 Men","brand":"Carolina Herrera","closestOurSite":"inspired-by-creed-aventus","aliases":[],"isDirectInspiration":false},{"id":"pop-frag-276","name":"212 VIP Men","brand":"Carolina Herrera","closestOurSite":"inspired-by-jpg-le-male","aliases":[],"isDirectInspiration":false},{"id":"pop-frag-277","name":"Explorer","brand":"Montblanc","closestOurSite":"inspired-by-creed-aventus","aliases":[],"isDirectInspiration":false},{"id":"pop-frag-278","name":"Explorer Platinum","brand":"Montblanc","closestOurSite":"inspired-by-creed-aventus","aliases":[],"isDirectInspiration":false},{"id":"pop-frag-279","name":"Legend","brand":"Montblanc","closestOurSite":"inspired-by-creed-aventus","aliases":[],"isDirectInspiration":false},{"id":"pop-frag-280","name":"Legend Spirit","brand":"Montblanc","closestOurSite":"inspired-by-creed-aventus","aliases":[],"isDirectInspiration":false},{"id":"pop-frag-281","name":"Individuel","brand":"Montblanc","closestOurSite":"inspired-by-jpg-le-male","aliases":[],"isDirectInspiration":false},{"id":"pop-frag-282","name":"Boss Bottled","brand":"Hugo Boss","closestOurSite":"inspired-by-creed-aventus","aliases":[],"isDirectInspiration":false},{"id":"pop-frag-283","name":"Boss Bottled Infinite","brand":"Hugo Boss","closestOurSite":"inspired-by-creed-aventus","aliases":[],"isDirectInspiration":false},{"id":"pop-frag-284","name":"Boss Bottled Elixir","brand":"Hugo Boss","closestOurSite":"inspired-by-creed-aventus","aliases":[],"isDirectInspiration":false},{"id":"pop-frag-285","name":"Boss Bottled Oud","brand":"Hugo Boss","closestOurSite":"inspired-by-creed-aventus","aliases":[],"isDirectInspiration":false},{"id":"pop-frag-286","name":"Hugo Man","brand":"Hugo Boss","closestOurSite":"inspired-by-creed-aventus","aliases":[],"isDirectInspiration":false},{"id":"pop-frag-287","name":"Boss The Scent","brand":"Hugo Boss","closestOurSite":"inspired-by-jpg-le-male","aliases":[],"isDirectInspiration":false},{"id":"pop-frag-288","name":"Boss The Scent Magnetic","brand":"Hugo Boss","closestOurSite":"inspired-by-jpg-le-male","aliases":[],"isDirectInspiration":false},{"id":"pop-frag-289","name":"Boss The Scent Elixir","brand":"Hugo Boss","closestOurSite":"inspired-by-jpg-le-male","aliases":[],"isDirectInspiration":false},{"id":"pop-frag-290","name":"Encre Noire","brand":"Lalique","closestOurSite":"inspired-by-creed-aventus","aliases":[],"isDirectInspiration":false},{"id":"pop-frag-291","name":"Encre Noire A L'Extreme","brand":"Lalique","closestOurSite":"inspired-by-creed-aventus","aliases":[],"isDirectInspiration":false},{"id":"pop-frag-292","name":"Encre Noire Sport","brand":"Lalique","closestOurSite":"inspired-by-creed-aventus","aliases":[],"isDirectInspiration":false},{"id":"pop-frag-293","name":"CK One","brand":"Calvin Klein","closestOurSite":"inspired-by-creed-aventus","aliases":[],"isDirectInspiration":false},{"id":"pop-frag-294","name":"CK Be","brand":"Calvin Klein","closestOurSite":"inspired-by-creed-aventus","aliases":[],"isDirectInspiration":false},{"id":"pop-frag-295","name":"Eternity for Men","brand":"Calvin Klein","closestOurSite":"inspired-by-creed-aventus","aliases":[],"isDirectInspiration":false},{"id":"pop-frag-296","name":"Eternity for Women","brand":"Calvin Klein","closestOurSite":"inspired-by-jpg-le-male","aliases":[],"isDirectInspiration":false},{"id":"pop-frag-297","name":"Obsession for Men","brand":"Calvin Klein","closestOurSite":"inspired-by-jpg-le-male","aliases":[],"isDirectInspiration":false},{"id":"pop-frag-298","name":"Obsession for Women","brand":"Calvin Klein","closestOurSite":"inspired-by-jpg-le-male","aliases":[],"isDirectInspiration":false},{"id":"pop-frag-299","name":"Euphoria Men","brand":"Calvin Klein","closestOurSite":"inspired-by-creed-aventus","aliases":[],"isDirectInspiration":false},{"id":"pop-frag-300","name":"Euphoria Women","brand":"Calvin Klein","closestOurSite":"inspired-by-jpg-le-male","aliases":[],"isDirectInspiration":false},{"id":"pop-frag-301","name":"Cool Water","brand":"Davidoff","closestOurSite":"inspired-by-creed-aventus","aliases":[],"isDirectInspiration":false},{"id":"pop-frag-302","name":"Cool Water Intense","brand":"Davidoff","closestOurSite":"inspired-by-jpg-le-male","aliases":[],"isDirectInspiration":false},{"id":"pop-frag-303","name":"Zino Davidoff","brand":"Davidoff","closestOurSite":"inspired-by-creed-aventus","aliases":[],"isDirectInspiration":false},{"id":"pop-frag-304","name":"Hero","brand":"Burberry","closestOurSite":"inspired-by-creed-aventus","aliases":[],"isDirectInspiration":false},{"id":"pop-frag-305","name":"Touch for Men","brand":"Burberry","closestOurSite":"inspired-by-creed-aventus","aliases":[],"isDirectInspiration":false},{"id":"pop-frag-306","name":"Touch for Women","brand":"Burberry","closestOurSite":"inspired-by-jpg-le-male","aliases":[],"isDirectInspiration":false},{"id":"pop-frag-307","name":"Brit for Men","brand":"Burberry","closestOurSite":"inspired-by-creed-aventus","aliases":[],"isDirectInspiration":false},{"id":"pop-frag-308","name":"Brit for Women","brand":"Burberry","closestOurSite":"inspired-by-jpg-le-male","aliases":[],"isDirectInspiration":false},{"id":"pop-frag-309","name":"Burberry Goddess","brand":"Burberry","closestOurSite":"inspired-by-jpg-le-male","aliases":[],"isDirectInspiration":false},{"id":"pop-frag-310","name":"London for Men","brand":"Burberry","closestOurSite":"inspired-by-creed-aventus","aliases":[],"isDirectInspiration":false},{"id":"pop-frag-311","name":"London for Women","brand":"Burberry","closestOurSite":"inspired-by-jpg-le-male","aliases":[],"isDirectInspiration":false},{"id":"pop-frag-312","name":"Weekend for Men","brand":"Burberry","closestOurSite":"inspired-by-creed-aventus","aliases":[],"isDirectInspiration":false},{"id":"pop-frag-313","name":"Weekend for Women","brand":"Burberry","closestOurSite":"inspired-by-jpg-le-male","aliases":[],"isDirectInspiration":false},{"id":"pop-frag-314","name":"Naxos","brand":"Xerjoff","closestOurSite":"inspired-by-jpg-le-male","aliases":[],"isDirectInspiration":false},{"id":"pop-frag-315","name":"Erba Pura","brand":"Xerjoff","closestOurSite":"inspired-by-jpg-le-male","aliases":[],"isDirectInspiration":false},{"id":"pop-frag-316","name":"Alexandria II","brand":"Xerjoff","closestOurSite":"inspired-by-creed-aventus","aliases":[],"isDirectInspiration":false},{"id":"pop-frag-317","name":"Mefisto","brand":"Xerjoff","closestOurSite":"inspired-by-creed-aventus","aliases":[],"isDirectInspiration":false},{"id":"pop-frag-318","name":"Renaissance","brand":"Xerjoff","closestOurSite":"inspired-by-creed-aventus","aliases":[],"isDirectInspiration":false},{"id":"pop-frag-319","name":"Uden","brand":"Xerjoff","closestOurSite":"inspired-by-creed-aventus","aliases":[],"isDirectInspiration":false},{"id":"pop-frag-320","name":"Santal 33","brand":"Le Labo","closestOurSite":"inspired-by-creed-aventus","aliases":[],"isDirectInspiration":false},{"id":"pop-frag-321","name":"Another 13","brand":"Le Labo","closestOurSite":"inspired-by-creed-aventus","aliases":[],"isDirectInspiration":false},{"id":"pop-frag-322","name":"Rose 31","brand":"Le Labo","closestOurSite":"inspired-by-jpg-le-male","aliases":[],"isDirectInspiration":false},{"id":"pop-frag-323","name":"Bergamote 22","brand":"Le Labo","closestOurSite":"inspired-by-creed-aventus","aliases":[],"isDirectInspiration":false},{"id":"pop-frag-324","name":"The Noir 29","brand":"Le Labo","closestOurSite":"inspired-by-creed-aventus","aliases":[],"isDirectInspiration":false},{"id":"pop-frag-325","name":"Cedrat Boise","brand":"Mancera","closestOurSite":"inspired-by-creed-aventus","aliases":[],"isDirectInspiration":false},{"id":"pop-frag-326","name":"Intense Cedrat Boise","brand":"Mancera","closestOurSite":"inspired-by-creed-aventus","aliases":[],"isDirectInspiration":false},{"id":"pop-frag-327","name":"Red Tobacco","brand":"Mancera","closestOurSite":"inspired-by-jpg-le-male","aliases":[],"isDirectInspiration":false},{"id":"pop-frag-328","name":"Instant Crush","brand":"Mancera","closestOurSite":"inspired-by-jpg-le-male","aliases":[],"isDirectInspiration":false},{"id":"pop-frag-329","name":"Arabians Tonka","brand":"Montale","closestOurSite":"inspired-by-jpg-le-male","aliases":[],"isDirectInspiration":false},{"id":"pop-frag-330","name":"Intense Cafe","brand":"Montale","closestOurSite":"inspired-by-jpg-le-male","aliases":[],"isDirectInspiration":false},{"id":"pop-frag-331","name":"Honey Aoud","brand":"Montale","closestOurSite":"inspired-by-jpg-le-male","aliases":[],"isDirectInspiration":false},{"id":"pop-frag-332","name":"Oud for Greatness","brand":"Initio Parfums","closestOurSite":"inspired-by-creed-aventus","aliases":[],"isDirectInspiration":false},{"id":"pop-frag-333","name":"Side Effect","brand":"Initio Parfums","closestOurSite":"inspired-by-jpg-le-male","aliases":[],"isDirectInspiration":false},{"id":"pop-frag-334","name":"Rehab","brand":"Initio Parfums","closestOurSite":"inspired-by-jpg-le-male","aliases":[],"isDirectInspiration":false},{"id":"pop-frag-335","name":"Joop! Homme","brand":"Joop!","closestOurSite":"inspired-by-jpg-le-male","aliases":[],"isDirectInspiration":false},{"id":"pop-frag-336","name":"Patchouli","brand":"Balenciaga","closestOurSite":"inspired-by-creed-aventus","aliases":[],"isDirectInspiration":false},{"id":"pop-frag-337","name":"Rose L'Eau","brand":"Jo Malone","closestOurSite":"inspired-by-jpg-le-male","aliases":[],"isDirectInspiration":false},{"id":"pop-frag-338","name":"Jasmine Silver","brand":"Coach","closestOurSite":"inspired-by-jpg-le-male","aliases":[],"isDirectInspiration":false},{"id":"pop-frag-339","name":"Blue Eau de","brand":"Yves Saint Laurent","closestOurSite":"inspired-by-creed-aventus","aliases":["ysl blue eau de"],"isDirectInspiration":false},{"id":"pop-frag-340","name":"Santal Intense","brand":"Prada","closestOurSite":"inspired-by-creed-aventus","aliases":[],"isDirectInspiration":false},{"id":"pop-frag-341","name":"Nuit Collector","brand":"Hugo Boss","closestOurSite":"inspired-by-creed-aventus","aliases":[],"isDirectInspiration":false},{"id":"pop-frag-342","name":"Vetiver Silver","brand":"Dior","closestOurSite":"inspired-by-creed-aventus","aliases":[],"isDirectInspiration":false},{"id":"pop-frag-343","name":"Vetiver Elixir","brand":"Lacoste","closestOurSite":"inspired-by-creed-aventus","aliases":[],"isDirectInspiration":false},{"id":"pop-frag-344","name":"Red Night","brand":"Jo Malone","closestOurSite":"inspired-by-creed-aventus","aliases":[],"isDirectInspiration":false},{"id":"pop-frag-345","name":"Musk Sensuelle","brand":"Giorgio Armani","closestOurSite":"inspired-by-jpg-le-male","aliases":[],"isDirectInspiration":false},{"id":"pop-frag-346","name":"Soir","brand":"Coach","closestOurSite":"inspired-by-creed-aventus","aliases":[],"isDirectInspiration":false},{"id":"pop-frag-347","name":"Jour Black","brand":"Azzaro","closestOurSite":"inspired-by-creed-aventus","aliases":[],"isDirectInspiration":false},{"id":"pop-frag-348","name":"Citrus Gold","brand":"Maison Francis Kurkdjian","closestOurSite":"inspired-by-creed-aventus","aliases":["mfk citrus gold"],"isDirectInspiration":false},{"id":"pop-frag-349","name":"Amber","brand":"Gucci","closestOurSite":"inspired-by-jpg-le-male","aliases":[],"isDirectInspiration":false},{"id":"pop-frag-350","name":"Citrus Fresh","brand":"Yves Saint Laurent","closestOurSite":"inspired-by-creed-aventus","aliases":["ysl citrus fresh"],"isDirectInspiration":false},{"id":"pop-frag-351","name":"Musk","brand":"Dunhill","closestOurSite":"inspired-by-jpg-le-male","aliases":[],"isDirectInspiration":false},{"id":"pop-frag-352","name":"Amber Absolu","brand":"Chanel","closestOurSite":"inspired-by-jpg-le-male","aliases":[],"isDirectInspiration":false},{"id":"pop-frag-353","name":"Oud","brand":"Jean Paul Gaultier","closestOurSite":"inspired-by-creed-aventus","aliases":["jpg oud"],"isDirectInspiration":false},{"id":"pop-frag-354","name":"Cedar Summer","brand":"Maison Francis Kurkdjian","closestOurSite":"inspired-by-creed-aventus","aliases":["mfk cedar summer"],"isDirectInspiration":false},{"id":"pop-frag-355","name":"Red Fresh","brand":"Bulgari","closestOurSite":"inspired-by-creed-aventus","aliases":[],"isDirectInspiration":false},{"id":"pop-frag-356","name":"Nuit Fresh","brand":"Creed","closestOurSite":"inspired-by-creed-aventus","aliases":[],"isDirectInspiration":false},{"id":"pop-frag-357","name":"Citrus Reserve","brand":"Kilian","closestOurSite":"inspired-by-creed-aventus","aliases":[],"isDirectInspiration":false},{"id":"pop-frag-358","name":"Rose Black","brand":"Jean Paul Gaultier","closestOurSite":"inspired-by-jpg-le-male","aliases":["jpg rose black"],"isDirectInspiration":false},{"id":"pop-frag-359","name":"Homme","brand":"Coach","closestOurSite":"inspired-by-creed-aventus","aliases":[],"isDirectInspiration":false},{"id":"pop-frag-360","name":"Neroli Intense","brand":"Amouage","closestOurSite":"inspired-by-creed-aventus","aliases":[],"isDirectInspiration":false},{"id":"pop-frag-361","name":"Leather Silver","brand":"Calvin Klein","closestOurSite":"inspired-by-creed-aventus","aliases":[],"isDirectInspiration":false},{"id":"pop-frag-362","name":"Vanilla Fresh","brand":"Marc Jacobs","closestOurSite":"inspired-by-jpg-le-male","aliases":[],"isDirectInspiration":false},{"id":"pop-frag-363","name":"Patchouli Eau de","brand":"Coach","closestOurSite":"inspired-by-creed-aventus","aliases":[],"isDirectInspiration":false},{"id":"pop-frag-364","name":"Cedar Reserve","brand":"Balenciaga","closestOurSite":"inspired-by-creed-aventus","aliases":[],"isDirectInspiration":false},{"id":"pop-frag-365","name":"Homme Silver","brand":"Marc Jacobs","closestOurSite":"inspired-by-creed-aventus","aliases":[],"isDirectInspiration":false},{"id":"pop-frag-366","name":"Jour Summer","brand":"Byredo","closestOurSite":"inspired-by-creed-aventus","aliases":[],"isDirectInspiration":false},{"id":"pop-frag-367","name":"Patchouli","brand":"Maison Francis Kurkdjian","closestOurSite":"inspired-by-creed-aventus","aliases":["mfk patchouli"],"isDirectInspiration":false},{"id":"pop-frag-368","name":"Red","brand":"Kilian","closestOurSite":"inspired-by-creed-aventus","aliases":[],"isDirectInspiration":false},{"id":"pop-frag-369","name":"Blue","brand":"Balenciaga","closestOurSite":"inspired-by-creed-aventus","aliases":[],"isDirectInspiration":false},{"id":"pop-frag-370","name":"Jour Fresh","brand":"Azzaro","closestOurSite":"inspired-by-creed-aventus","aliases":[],"isDirectInspiration":false},{"id":"pop-frag-371","name":"Rose Sensuelle","brand":"Dior","closestOurSite":"inspired-by-jpg-le-male","aliases":[],"isDirectInspiration":false},{"id":"pop-frag-372","name":"Soir","brand":"Versace","closestOurSite":"inspired-by-creed-aventus","aliases":[],"isDirectInspiration":false},{"id":"pop-frag-373","name":"Amber Silver","brand":"Bulgari","closestOurSite":"inspired-by-jpg-le-male","aliases":[],"isDirectInspiration":false},{"id":"pop-frag-374","name":"Soir Elixir","brand":"Marc Jacobs","closestOurSite":"inspired-by-creed-aventus","aliases":[],"isDirectInspiration":false},{"id":"pop-frag-375","name":"Oud","brand":"Viktor & Rolf","closestOurSite":"inspired-by-creed-aventus","aliases":[],"isDirectInspiration":false},{"id":"pop-frag-376","name":"Citrus","brand":"Jo Malone","closestOurSite":"inspired-by-creed-aventus","aliases":[],"isDirectInspiration":false},{"id":"pop-frag-377","name":"Vanilla","brand":"Versace","closestOurSite":"inspired-by-jpg-le-male","aliases":[],"isDirectInspiration":false},{"id":"pop-frag-378","name":"Homme Extreme","brand":"Lancome","closestOurSite":"inspired-by-creed-aventus","aliases":[],"isDirectInspiration":false},{"id":"pop-frag-379","name":"Sport","brand":"Cartier","closestOurSite":"inspired-by-creed-aventus","aliases":[],"isDirectInspiration":false},{"id":"pop-frag-380","name":"Citrus Summer","brand":"Azzaro","closestOurSite":"inspired-by-creed-aventus","aliases":[],"isDirectInspiration":false},{"id":"pop-frag-381","name":"Jasmine Limited Edition","brand":"Bulgari","closestOurSite":"inspired-by-jpg-le-male","aliases":[],"isDirectInspiration":false},{"id":"pop-frag-382","name":"Leather Absolu","brand":"Cartier","closestOurSite":"inspired-by-creed-aventus","aliases":[],"isDirectInspiration":false},{"id":"pop-frag-383","name":"Red","brand":"Amouage","closestOurSite":"inspired-by-creed-aventus","aliases":[],"isDirectInspiration":false},{"id":"pop-frag-384","name":"Rose Gold","brand":"Coach","closestOurSite":"inspired-by-jpg-le-male","aliases":[],"isDirectInspiration":false},{"id":"pop-frag-385","name":"Femme Limited Edition","brand":"Gucci","closestOurSite":"inspired-by-creed-aventus","aliases":[],"isDirectInspiration":false},{"id":"pop-frag-386","name":"Jour Intense","brand":"Prada","closestOurSite":"inspired-by-creed-aventus","aliases":[],"isDirectInspiration":false},{"id":"pop-frag-387","name":"Neroli Sensuelle","brand":"Bulgari","closestOurSite":"inspired-by-jpg-le-male","aliases":[],"isDirectInspiration":false},{"id":"pop-frag-388","name":"Vetiver Silver","brand":"Tom Ford","closestOurSite":"inspired-by-creed-aventus","aliases":[],"isDirectInspiration":false},{"id":"pop-frag-389","name":"Bergamot Night","brand":"Paco Rabanne","closestOurSite":"inspired-by-creed-aventus","aliases":[],"isDirectInspiration":false},{"id":"pop-frag-390","name":"Patchouli Sport","brand":"Hermès","closestOurSite":"inspired-by-creed-aventus","aliases":[],"isDirectInspiration":false},{"id":"pop-frag-391","name":"Citrus Sport","brand":"Calvin Klein","closestOurSite":"inspired-by-creed-aventus","aliases":[],"isDirectInspiration":false},{"id":"pop-frag-392","name":"Amber Intense","brand":"Byredo","closestOurSite":"inspired-by-jpg-le-male","aliases":[],"isDirectInspiration":false},{"id":"pop-frag-393","name":"Nuit","brand":"Hugo Boss","closestOurSite":"inspired-by-creed-aventus","aliases":[],"isDirectInspiration":false},{"id":"pop-frag-394","name":"Soir Black","brand":"Coach","closestOurSite":"inspired-by-creed-aventus","aliases":[],"isDirectInspiration":false},{"id":"pop-frag-395","name":"Aqua Fresh","brand":"Dunhill","closestOurSite":"inspired-by-creed-aventus","aliases":[],"isDirectInspiration":false},{"id":"pop-frag-396","name":"Green Elixir","brand":"Dolce & Gabbana","closestOurSite":"inspired-by-creed-aventus","aliases":["dg green elixir","d&g green elixir"],"isDirectInspiration":false},{"id":"pop-frag-397","name":"Nuit","brand":"Versace","closestOurSite":"inspired-by-creed-aventus","aliases":[],"isDirectInspiration":false},{"id":"pop-frag-398","name":"Neroli Fresh","brand":"Carolina Herrera","closestOurSite":"inspired-by-creed-aventus","aliases":[],"isDirectInspiration":false},{"id":"pop-frag-399","name":"Musk Eau de","brand":"Jean Paul Gaultier","closestOurSite":"inspired-by-jpg-le-male","aliases":["jpg musk eau de"],"isDirectInspiration":false},{"id":"pop-frag-400","name":"Amber","brand":"Estee Lauder","closestOurSite":"inspired-by-jpg-le-male","aliases":[],"isDirectInspiration":false},{"id":"pop-frag-401","name":"Musk Fresh","brand":"Bulgari","closestOurSite":"inspired-by-jpg-le-male","aliases":[],"isDirectInspiration":false},{"id":"pop-frag-402","name":"Oud Night","brand":"Lacoste","closestOurSite":"inspired-by-creed-aventus","aliases":[],"isDirectInspiration":false},{"id":"pop-frag-403","name":"Cedar Sport","brand":"Jimmy Choo","closestOurSite":"inspired-by-creed-aventus","aliases":[],"isDirectInspiration":false},{"id":"pop-frag-404","name":"Cedar","brand":"Yves Saint Laurent","closestOurSite":"inspired-by-creed-aventus","aliases":["ysl cedar"],"isDirectInspiration":false},{"id":"pop-frag-405","name":"Cedar Fresh","brand":"Valentino","closestOurSite":"inspired-by-creed-aventus","aliases":[],"isDirectInspiration":false},{"id":"pop-frag-406","name":"Vetiver Gold","brand":"Dunhill","closestOurSite":"inspired-by-creed-aventus","aliases":[],"isDirectInspiration":false},{"id":"pop-frag-407","name":"Jasmine Summer","brand":"Tom Ford","closestOurSite":"inspired-by-jpg-le-male","aliases":[],"isDirectInspiration":false},{"id":"pop-frag-408","name":"Homme Elixir","brand":"Azzaro","closestOurSite":"inspired-by-creed-aventus","aliases":[],"isDirectInspiration":false},{"id":"pop-frag-409","name":"Aqua Limited Edition","brand":"Lacoste","closestOurSite":"inspired-by-creed-aventus","aliases":[],"isDirectInspiration":false},{"id":"pop-frag-410","name":"Nuit","brand":"Givenchy","closestOurSite":"inspired-by-creed-aventus","aliases":[],"isDirectInspiration":false},{"id":"pop-frag-411","name":"Santal Limited Edition","brand":"Boucheron","closestOurSite":"inspired-by-creed-aventus","aliases":[],"isDirectInspiration":false},{"id":"pop-frag-412","name":"Aqua Reserve","brand":"Kilian","closestOurSite":"inspired-by-creed-aventus","aliases":[],"isDirectInspiration":false},{"id":"pop-frag-413","name":"Amber Gold","brand":"Hugo Boss","closestOurSite":"inspired-by-jpg-le-male","aliases":[],"isDirectInspiration":false},{"id":"pop-frag-414","name":"Santal","brand":"Cartier","closestOurSite":"inspired-by-creed-aventus","aliases":[],"isDirectInspiration":false},{"id":"pop-frag-415","name":"Amber Fresh","brand":"Hugo Boss","closestOurSite":"inspired-by-jpg-le-male","aliases":[],"isDirectInspiration":false},{"id":"pop-frag-416","name":"Red Summer","brand":"Amouage","closestOurSite":"inspired-by-creed-aventus","aliases":[],"isDirectInspiration":false},{"id":"pop-frag-417","name":"Amber Eau de","brand":"Jean Paul Gaultier","closestOurSite":"inspired-by-jpg-le-male","aliases":["jpg amber eau de"],"isDirectInspiration":false},{"id":"pop-frag-418","name":"Rose Intense","brand":"Giorgio Armani","closestOurSite":"inspired-by-jpg-le-male","aliases":[],"isDirectInspiration":false},{"id":"pop-frag-419","name":"Soir Extreme","brand":"Jo Malone","closestOurSite":"inspired-by-creed-aventus","aliases":[],"isDirectInspiration":false},{"id":"pop-frag-420","name":"Cedar L'Eau","brand":"Coach","closestOurSite":"inspired-by-creed-aventus","aliases":[],"isDirectInspiration":false},{"id":"pop-frag-421","name":"Rose Limited Edition","brand":"Gucci","closestOurSite":"inspired-by-jpg-le-male","aliases":[],"isDirectInspiration":false},{"id":"pop-frag-422","name":"Jasmine Silver","brand":"Calvin Klein","closestOurSite":"inspired-by-jpg-le-male","aliases":[],"isDirectInspiration":false},{"id":"pop-frag-423","name":"Red Collector","brand":"Tom Ford","closestOurSite":"inspired-by-creed-aventus","aliases":[],"isDirectInspiration":false},{"id":"pop-frag-424","name":"Red Gold","brand":"Bulgari","closestOurSite":"inspired-by-creed-aventus","aliases":[],"isDirectInspiration":false},{"id":"pop-frag-425","name":"Bergamot Fresh","brand":"Lancome","closestOurSite":"inspired-by-creed-aventus","aliases":[],"isDirectInspiration":false},{"id":"pop-frag-426","name":"Red Intense","brand":"Lancome","closestOurSite":"inspired-by-creed-aventus","aliases":[],"isDirectInspiration":false},{"id":"pop-frag-427","name":"Red Absolu","brand":"Cartier","closestOurSite":"inspired-by-creed-aventus","aliases":[],"isDirectInspiration":false},{"id":"pop-frag-428","name":"Jour","brand":"Jo Malone","closestOurSite":"inspired-by-creed-aventus","aliases":[],"isDirectInspiration":false},{"id":"pop-frag-429","name":"Jour Reserve","brand":"Versace","closestOurSite":"inspired-by-creed-aventus","aliases":[],"isDirectInspiration":false},{"id":"pop-frag-430","name":"Red L'Eau","brand":"Byredo","closestOurSite":"inspired-by-creed-aventus","aliases":[],"isDirectInspiration":false},{"id":"pop-frag-431","name":"Blue Night","brand":"Chloe","closestOurSite":"inspired-by-creed-aventus","aliases":[],"isDirectInspiration":false},{"id":"pop-frag-432","name":"Aqua Eau de","brand":"Marc Jacobs","closestOurSite":"inspired-by-creed-aventus","aliases":[],"isDirectInspiration":false},{"id":"pop-frag-433","name":"Soir","brand":"Dunhill","closestOurSite":"inspired-by-creed-aventus","aliases":[],"isDirectInspiration":false},{"id":"pop-frag-434","name":"Rose Sport","brand":"Chanel","closestOurSite":"inspired-by-jpg-le-male","aliases":[],"isDirectInspiration":false},{"id":"pop-frag-435","name":"Musk Sensuelle","brand":"Balenciaga","closestOurSite":"inspired-by-jpg-le-male","aliases":[],"isDirectInspiration":false},{"id":"pop-frag-436","name":"Nuit Black","brand":"Chloe","closestOurSite":"inspired-by-creed-aventus","aliases":[],"isDirectInspiration":false},{"id":"pop-frag-437","name":"Femme Absolu","brand":"Lancome","closestOurSite":"inspired-by-creed-aventus","aliases":[],"isDirectInspiration":false},{"id":"pop-frag-438","name":"Blue Sensuelle","brand":"Viktor & Rolf","closestOurSite":"inspired-by-jpg-le-male","aliases":[],"isDirectInspiration":false},{"id":"pop-frag-439","name":"Aqua Fresh","brand":"Marc Jacobs","closestOurSite":"inspired-by-creed-aventus","aliases":[],"isDirectInspiration":false},{"id":"pop-frag-440","name":"Green L'Eau","brand":"Amouage","closestOurSite":"inspired-by-creed-aventus","aliases":[],"isDirectInspiration":false},{"id":"pop-frag-441","name":"Oud Eau de","brand":"Parfums de Marly","closestOurSite":"inspired-by-creed-aventus","aliases":["pdm oud eau de"],"isDirectInspiration":false},{"id":"pop-frag-442","name":"Bergamot Intense","brand":"Cartier","closestOurSite":"inspired-by-creed-aventus","aliases":[],"isDirectInspiration":false},{"id":"pop-frag-443","name":"Patchouli L'Eau","brand":"Valentino","closestOurSite":"inspired-by-creed-aventus","aliases":[],"isDirectInspiration":false},{"id":"pop-frag-444","name":"Red","brand":"Paco Rabanne","closestOurSite":"inspired-by-creed-aventus","aliases":[],"isDirectInspiration":false},{"id":"pop-frag-445","name":"Sport Black","brand":"Jean Paul Gaultier","closestOurSite":"inspired-by-creed-aventus","aliases":["jpg sport black"],"isDirectInspiration":false},{"id":"pop-frag-446","name":"Green","brand":"Paco Rabanne","closestOurSite":"inspired-by-creed-aventus","aliases":[],"isDirectInspiration":false},{"id":"pop-frag-447","name":"Homme Black","brand":"Jimmy Choo","closestOurSite":"inspired-by-creed-aventus","aliases":[],"isDirectInspiration":false},{"id":"pop-frag-448","name":"Oud Collector","brand":"Dunhill","closestOurSite":"inspired-by-creed-aventus","aliases":[],"isDirectInspiration":false},{"id":"pop-frag-449","name":"Jour Absolu","brand":"Hermès","closestOurSite":"inspired-by-creed-aventus","aliases":[],"isDirectInspiration":false},{"id":"pop-frag-450","name":"Leather L'Eau","brand":"Cartier","closestOurSite":"inspired-by-creed-aventus","aliases":[],"isDirectInspiration":false},{"id":"pop-frag-451","name":"Rose","brand":"Amouage","closestOurSite":"inspired-by-jpg-le-male","aliases":[],"isDirectInspiration":false},{"id":"pop-frag-452","name":"Oud Night","brand":"Giorgio Armani","closestOurSite":"inspired-by-creed-aventus","aliases":[],"isDirectInspiration":false},{"id":"pop-frag-453","name":"Amber Reserve","brand":"Hermès","closestOurSite":"inspired-by-jpg-le-male","aliases":[],"isDirectInspiration":false},{"id":"pop-frag-454","name":"Citrus L'Eau","brand":"Dunhill","closestOurSite":"inspired-by-creed-aventus","aliases":[],"isDirectInspiration":false},{"id":"pop-frag-455","name":"Cedar Intense","brand":"Montblanc","closestOurSite":"inspired-by-creed-aventus","aliases":[],"isDirectInspiration":false},{"id":"pop-frag-456","name":"Amber Gold","brand":"Lancome","closestOurSite":"inspired-by-jpg-le-male","aliases":[],"isDirectInspiration":false},{"id":"pop-frag-457","name":"Oud L'Eau","brand":"Hugo Boss","closestOurSite":"inspired-by-creed-aventus","aliases":[],"isDirectInspiration":false},{"id":"pop-frag-458","name":"Leather Elixir","brand":"Paco Rabanne","closestOurSite":"inspired-by-creed-aventus","aliases":[],"isDirectInspiration":false},{"id":"pop-frag-459","name":"Blue Limited Edition","brand":"Burberry","closestOurSite":"inspired-by-creed-aventus","aliases":[],"isDirectInspiration":false},{"id":"pop-frag-460","name":"Femme Absolu","brand":"Kilian","closestOurSite":"inspired-by-creed-aventus","aliases":[],"isDirectInspiration":false},{"id":"pop-frag-461","name":"Jasmine Reserve","brand":"Jo Malone","closestOurSite":"inspired-by-jpg-le-male","aliases":[],"isDirectInspiration":false},{"id":"pop-frag-462","name":"Vetiver Gold","brand":"Montblanc","closestOurSite":"inspired-by-creed-aventus","aliases":[],"isDirectInspiration":false},{"id":"pop-frag-463","name":"Homme Elixir","brand":"Lancome","closestOurSite":"inspired-by-creed-aventus","aliases":[],"isDirectInspiration":false},{"id":"pop-frag-464","name":"Vetiver Black","brand":"Tom Ford","closestOurSite":"inspired-by-creed-aventus","aliases":[],"isDirectInspiration":false},{"id":"pop-frag-465","name":"Vetiver Elixir","brand":"Dior","closestOurSite":"inspired-by-creed-aventus","aliases":[],"isDirectInspiration":false},{"id":"pop-frag-466","name":"Nuit Elixir","brand":"Versace","closestOurSite":"inspired-by-creed-aventus","aliases":[],"isDirectInspiration":false},{"id":"pop-frag-467","name":"Vanilla","brand":"Burberry","closestOurSite":"inspired-by-jpg-le-male","aliases":[],"isDirectInspiration":false},{"id":"pop-frag-468","name":"Citrus","brand":"Versace","closestOurSite":"inspired-by-creed-aventus","aliases":[],"isDirectInspiration":false},{"id":"pop-frag-469","name":"Bergamot","brand":"Viktor & Rolf","closestOurSite":"inspired-by-creed-aventus","aliases":[],"isDirectInspiration":false},{"id":"pop-frag-470","name":"Jasmine Gold","brand":"Dolce & Gabbana","closestOurSite":"inspired-by-jpg-le-male","aliases":["dg jasmine gold","d&g jasmine gold"],"isDirectInspiration":false},{"id":"pop-frag-471","name":"Jasmine Limited Edition","brand":"Dior","closestOurSite":"inspired-by-jpg-le-male","aliases":[],"isDirectInspiration":false},{"id":"pop-frag-472","name":"Homme Sensuelle","brand":"Bulgari","closestOurSite":"inspired-by-jpg-le-male","aliases":[],"isDirectInspiration":false},{"id":"pop-frag-473","name":"Green Gold","brand":"Paco Rabanne","closestOurSite":"inspired-by-creed-aventus","aliases":[],"isDirectInspiration":false},{"id":"pop-frag-474","name":"Green Intense","brand":"Prada","closestOurSite":"inspired-by-creed-aventus","aliases":[],"isDirectInspiration":false},{"id":"pop-frag-475","name":"Nuit Limited Edition","brand":"Jo Malone","closestOurSite":"inspired-by-creed-aventus","aliases":[],"isDirectInspiration":false},{"id":"pop-frag-476","name":"Blue Extreme","brand":"Viktor & Rolf","closestOurSite":"inspired-by-creed-aventus","aliases":[],"isDirectInspiration":false},{"id":"pop-frag-477","name":"Femme Elixir","brand":"Yves Saint Laurent","closestOurSite":"inspired-by-creed-aventus","aliases":["ysl femme elixir"],"isDirectInspiration":false},{"id":"pop-frag-478","name":"Cedar L'Eau","brand":"Davidoff","closestOurSite":"inspired-by-creed-aventus","aliases":[],"isDirectInspiration":false},{"id":"pop-frag-479","name":"Citrus Fresh","brand":"Creed","closestOurSite":"inspired-by-creed-aventus","aliases":[],"isDirectInspiration":false},{"id":"pop-frag-480","name":"Bergamot Absolu","brand":"Lancome","closestOurSite":"inspired-by-creed-aventus","aliases":[],"isDirectInspiration":false},{"id":"pop-frag-481","name":"Oud Summer","brand":"Jean Paul Gaultier","closestOurSite":"inspired-by-creed-aventus","aliases":["jpg oud summer"],"isDirectInspiration":false},{"id":"pop-frag-482","name":"Musk Elixir","brand":"Versace","closestOurSite":"inspired-by-jpg-le-male","aliases":[],"isDirectInspiration":false},{"id":"pop-frag-483","name":"Citrus Sport","brand":"Creed","closestOurSite":"inspired-by-creed-aventus","aliases":[],"isDirectInspiration":false},{"id":"pop-frag-484","name":"Blue","brand":"Maison Francis Kurkdjian","closestOurSite":"inspired-by-creed-aventus","aliases":["mfk blue"],"isDirectInspiration":false},{"id":"pop-frag-485","name":"Citrus Black","brand":"Calvin Klein","closestOurSite":"inspired-by-creed-aventus","aliases":[],"isDirectInspiration":false},{"id":"pop-frag-486","name":"Cedar","brand":"Paco Rabanne","closestOurSite":"inspired-by-creed-aventus","aliases":[],"isDirectInspiration":false},{"id":"pop-frag-487","name":"Vetiver Reserve","brand":"Givenchy","closestOurSite":"inspired-by-creed-aventus","aliases":[],"isDirectInspiration":false},{"id":"pop-frag-488","name":"Oud Elixir","brand":"Lancome","closestOurSite":"inspired-by-creed-aventus","aliases":[],"isDirectInspiration":false},{"id":"pop-frag-489","name":"Sport","brand":"Jo Malone","closestOurSite":"inspired-by-creed-aventus","aliases":[],"isDirectInspiration":false},{"id":"pop-frag-490","name":"Soir Night","brand":"Byredo","closestOurSite":"inspired-by-creed-aventus","aliases":[],"isDirectInspiration":false},{"id":"pop-frag-491","name":"Soir L'Eau","brand":"Lancome","closestOurSite":"inspired-by-creed-aventus","aliases":[],"isDirectInspiration":false},{"id":"pop-frag-492","name":"Vanilla Eau de","brand":"Hugo Boss","closestOurSite":"inspired-by-jpg-le-male","aliases":[],"isDirectInspiration":false},{"id":"pop-frag-493","name":"Citrus Sport","brand":"Estee Lauder","closestOurSite":"inspired-by-creed-aventus","aliases":[],"isDirectInspiration":false},{"id":"pop-frag-494","name":"Citrus Night","brand":"Amouage","closestOurSite":"inspired-by-creed-aventus","aliases":[],"isDirectInspiration":false},{"id":"pop-frag-495","name":"Jour Absolu","brand":"Montblanc","closestOurSite":"inspired-by-creed-aventus","aliases":[],"isDirectInspiration":false},{"id":"pop-frag-496","name":"Green Intense","brand":"Lacoste","closestOurSite":"inspired-by-creed-aventus","aliases":[],"isDirectInspiration":false},{"id":"pop-frag-497","name":"Vanilla Absolu","brand":"Chloe","closestOurSite":"inspired-by-jpg-le-male","aliases":[],"isDirectInspiration":false},{"id":"pop-frag-498","name":"Green Reserve","brand":"Burberry","closestOurSite":"inspired-by-creed-aventus","aliases":[],"isDirectInspiration":false},{"id":"pop-frag-499","name":"Bergamot Silver","brand":"Giorgio Armani","closestOurSite":"inspired-by-creed-aventus","aliases":[],"isDirectInspiration":false}]